domcheck/__init__.py
domcheck/strategies.py
domcheck-1.1.4.dist-info/DESCRIPTION.rst
domcheck-1.1.4.dist-info/METADATA
domcheck-1.1.4.dist-info/metadata.json
domcheck-1.1.4.dist-info/RECORD
domcheck-1.1.4.dist-info/top_level.txt
domcheck-1.1.4.dist-info/WHEEL
